apresenta/__init__.py
apresenta/cortar.py
apresenta/main.py
apresenta-0.1.0.dist-info/METADATA
apresenta-0.1.0.dist-info/WHEEL
apresenta-0.1.0.dist-info/entry_points.txt
apresenta-0.1.0.dist-info/RECORD
