Metadata-Version: 2.4
Name: apresenta
Version: 0.1.0
Summary: Apresenta is a command-line toolkit for automatic narration of presentation videos.
Author: Otávio Barradas
Requires-Python: >=3.13
Requires-Dist: moviepy>=2.1.2
Requires-Dist: typer>=0.15.4
